dotable/__init__.py
dotable-0.1.1.dist-info/DESCRIPTION.rst
dotable-0.1.1.dist-info/METADATA
dotable-0.1.1.dist-info/RECORD
dotable-0.1.1.dist-info/WHEEL
dotable-0.1.1.dist-info/metadata.json
dotable-0.1.1.dist-info/top_level.txt
