Metadata-Version: 2.0
Name: dotable
Version: 0.1.1
Summary: A module for accessing nested lists and dictionaries using json style dot notation.
Home-page: https://github.com/MarcMeszaros/dotable
Author: Marc Meszaros
Author-email: me@marcmeszaros.com
License: Apache 2
Platform: UNKNOWN
Classifier: Development Status :: 4 - Beta
Classifier: Intended Audience :: Developers
Classifier: License :: OSI Approved :: Apache Software License
Classifier: Programming Language :: Python :: 2
Classifier: Programming Language :: Python :: 2.7
Classifier: Programming Language :: Python :: 3
Classifier: Programming Language :: Python :: 3.3
Classifier: Programming Language :: Python :: 3.4
Classifier: Programming Language :: Python :: 3.5
